odoo/addons/cooperator/README.rst
odoo/addons/cooperator/__init__.py
odoo/addons/cooperator/__manifest__.py
odoo/addons/cooperator/data/data.xml
odoo/addons/cooperator/data/mail_template_data.xml
odoo/addons/cooperator/demo/coop.xml
odoo/addons/cooperator/demo/users.xml
odoo/addons/cooperator/i18n/ca.po
odoo/addons/cooperator/i18n/ca_ES.po
odoo/addons/cooperator/i18n/cooperator.pot
odoo/addons/cooperator/i18n/es.po
odoo/addons/cooperator/i18n/fr.po
odoo/addons/cooperator/i18n/fr_BE.po
odoo/addons/cooperator/i18n/it.po
odoo/addons/cooperator/i18n/nl_BE.po
odoo/addons/cooperator/migrations/12.0.3.1.0/pre-migration.py
odoo/addons/cooperator/migrations/12.0.3.3.1/pre-migration.py
odoo/addons/cooperator/migrations/12.0.4.0.1/pre-migration.py
odoo/addons/cooperator/migrations/12.0.4.1.0/pre-migration.py
odoo/addons/cooperator/migrations/12.0.4.1.1/post-migration.py
odoo/addons/cooperator/migrations/12.0.5.0.0/pre-migration.py
odoo/addons/cooperator/migrations/12.0.6.0.0/post-fix_subscription_request_names.py
odoo/addons/cooperator/migrations/12.0.6.0.0/post-remove_subscription_request_subscription_type.py
odoo/addons/cooperator/migrations/8.0.1.0/pre-migration.py
odoo/addons/cooperator/models/__init__.py
odoo/addons/cooperator/models/account_invoice.py
odoo/addons/cooperator/models/account_journal.py
odoo/addons/cooperator/models/company.py
odoo/addons/cooperator/models/mail_template.py
odoo/addons/cooperator/models/operation_request.py
odoo/addons/cooperator/models/partner.py
odoo/addons/cooperator/models/product.py
odoo/addons/cooperator/models/share_line.py
odoo/addons/cooperator/models/subscription_register.py
odoo/addons/cooperator/models/subscription_request.py
odoo/addons/cooperator/readme/CONTRIBUTORS.rst
odoo/addons/cooperator/readme/DESCRIPTION.rst
odoo/addons/cooperator/readme/HISTORY.rst
odoo/addons/cooperator/readme/INSTALL.rst
odoo/addons/cooperator/readme/ROADMAP.rst
odoo/addons/cooperator/readme/USAGE.rst
odoo/addons/cooperator/report/__init__.py
odoo12_addon_cooperator-12.0.6.5.0.dist-info/METADATA
odoo12_addon_cooperator-12.0.6.5.0.dist-info/WHEEL
odoo12_addon_cooperator-12.0.6.5.0.dist-info/top_level.txt
odoo12_addon_cooperator-12.0.6.5.0.dist-info/RECORD
