Metadata-Version: 2.1
Name: odoo12-addon-cooperator
Version: 12.0.6.5.0
Summary: Manage your cooperators
Home-page: https://github.com/OCA/cooperative
Author: Coop IT Easy SC, Odoo Community Association (OCA)
Author-email: support@odoo-community.org
License: AGPL-3
Platform: UNKNOWN
Classifier: Programming Language :: Python
Classifier: Framework :: Odoo
Classifier: Framework :: Odoo :: 12.0
Classifier: License :: OSI Approved :: GNU Affero General Public License v3
Requires-Python: >=3.5
Requires-Dist: odoo12-addon-partner-contact-birthdate
Requires-Dist: odoo12-addon-partner-contact-gender
Requires-Dist: odoo12-addon-partner-firstname
Requires-Dist: odoo <12.1dev,>=12.0a
